{
  "updated": "2026-06-18T10:25:39.016Z",
  "source": "https://forum.theeastpacific.com/latest.rss",
  "items": [
    {
      "title": "[A-2026-32] Amendment to the Endorsement Caps Act",
      "url": "https://forum.theeastpacific.com/t/a-2026-32-amendment-to-the-endorsement-caps-act/19883",
      "author": "Ladona",
      "date": "2026-06-16"
    },
    {
      "title": "[PROPOSAL] Repeal: “Nuclear Testing Protocol”",
      "url": "https://forum.theeastpacific.com/t/proposal-repeal-nuclear-testing-protocol/19881",
      "author": "Bai_Lung",
      "date": "2026-06-16"
    },
    {
      "title": "Operation Lightning Plains",
      "url": "https://forum.theeastpacific.com/t/operation-lightning-plains/19880",
      "author": "American-Cascadia",
      "date": "2026-06-16"
    },
    {
      "title": "[T-2026-31] Ratification of The Laputan Compact",
      "url": "https://forum.theeastpacific.com/t/t-2026-31-ratification-of-the-laputan-compact/19879",
      "author": "Ladona",
      "date": "2026-06-15"
    },
    {
      "title": "[PROPOSAL] Repeal \"Condemn Lone Wolves United\"",
      "url": "https://forum.theeastpacific.com/t/proposal-repeal-condemn-lone-wolves-united/19878",
      "author": "Bai_Lung",
      "date": "2026-06-15"
    },
    {
      "title": "[NOMINATION] Citizenship Official: Waterfall State / Dimitri",
      "url": "https://forum.theeastpacific.com/t/nomination-citizenship-official-waterfall-state-dimitri/19877",
      "author": "Sammy23",
      "date": "2026-06-14"
    },
    {
      "title": "[Resignation] Cappedore",
      "url": "https://forum.theeastpacific.com/t/resignation-cappedore/19876",
      "author": "Cappedore",
      "date": "2026-06-13"
    },
    {
      "title": "[PASSED] Repeal: “The Right to a Lawful Divorce”",
      "url": "https://forum.theeastpacific.com/t/passed-repeal-the-right-to-a-lawful-divorce/19874",
      "author": "Bai_Lung",
      "date": "2026-06-12"
    },
    {
      "title": "Antilias Claim",
      "url": "https://forum.theeastpacific.com/t/antilias-claim/19872",
      "author": "estyquesada",
      "date": "2026-06-10"
    },
    {
      "title": "Welcome Liberza",
      "url": "https://forum.theeastpacific.com/t/welcome-liberza/19870",
      "author": "Liberza",
      "date": "2026-06-10"
    }
  ]
}